graphragzen/CLI/make_graph/__init__.py
graphragzen/CLI/make_graph/__main__.py
graphragzen/CLI/query/__init__.py
graphragzen/CLI/query/__main__.py
graphragzen/__init__.py
graphragzen/async_tools/__init__.py
graphragzen/async_tools/async_test.bla
graphragzen/async_tools/async_tools.py
graphragzen/clustering/__init__.py
graphragzen/clustering/describe.py
graphragzen/clustering/leiden.py
graphragzen/clustering/llm_output_structures.py
graphragzen/clustering/util.py
graphragzen/entity_extraction/__init__.py
graphragzen/entity_extraction/extract_entities.py
graphragzen/entity_extraction/llm_output_structures.py
graphragzen/entity_extraction/typing.py
graphragzen/entity_extraction/utils.py
graphragzen/examples/__init__.py
graphragzen/examples/autotune_custom_prompts.py
graphragzen/examples/generate_entity_graph.py
graphragzen/examples/query.py
graphragzen/llm/__init__.py
graphragzen/llm/base_llm.py
graphragzen/llm/llama_cpp_models.py
graphragzen/llm/openAI_API_client.py
graphragzen/llm/typing.py
graphragzen/load_documents/__init__.py
graphragzen/load_documents/load_documents.py
graphragzen/merge/__init__.py
graphragzen/merge/merge_features.py
graphragzen/merge/merge_nodes.py
graphragzen/merge/typing.py
graphragzen/merge/utils.py
graphragzen/preprocessing/__init__.py
graphragzen/preprocessing/preprocess.py
graphragzen/prompt_tuning/__init__.py
graphragzen/prompt_tuning/entities.py
graphragzen/prompt_tuning/llm_output_structures.py
graphragzen/prompt_tuning/summarization.py
graphragzen/prompt_tuning/utils.py
graphragzen/prompts/__init__.py
graphragzen/prompts/default_prompts/__init__.py
graphragzen/prompts/default_prompts/cluster_description_prompts.py
graphragzen/prompts/default_prompts/entity_extraction_prompts.py
graphragzen/prompts/default_prompts/local_search_prompts.py
graphragzen/prompts/default_prompts/summarization_prompts.py
graphragzen/prompts/prompt_tuning/__init__.py
graphragzen/prompts/prompt_tuning/domain.py
graphragzen-0.3.0.dist-info/LICENSE
graphragzen-0.3.0.dist-info/LICENSE.md
graphragzen-0.3.0.dist-info/METADATA
graphragzen-0.3.0.dist-info/WHEEL
graphragzen-0.3.0.dist-info/RECORD
