Metadata-Version: 2.1
Name: graphragzen
Version: 0.3.0
Summary: 
Home-page: https://github.com/benste/GraphRAGZen/
Author: benste
Author-email: benstmrs@gmail.com
Requires-Python: >=3.10,<=3.12
Classifier: Programming Language :: Python :: 3
Classifier: Programming Language :: Python :: 3.10
Classifier: Programming Language :: Python :: 3.11
Classifier: Programming Language :: Python :: 3.12
Requires-Dist: einops (>=0.8.0,<0.9.0)
Requires-Dist: jsonref (>=1.1.0,<2.0.0)
Requires-Dist: leidenalg (==0.10.2)
Requires-Dist: llama-cpp-python (>=0.2.87,<0.3.0)
Requires-Dist: llama-prompter (==0.2.2)
Requires-Dist: networkx (>=3.3,<4.0)
Requires-Dist: openai (>=1.43.0,<2.0.0)
Requires-Dist: pandas (>=2.2.2,<3.0.0)
Requires-Dist: pyarrow (>=17.0.0,<18.0.0)
Requires-Dist: pydantic (>=2.7.0)
Requires-Dist: qdrant-client[fastembed] (>=1.11.0,<2.0.0)
Requires-Dist: sentence-transformers (>=3.0.1,<4.0.0)
Requires-Dist: tiktoken (>=0.7.0,<0.8.0)
Requires-Dist: transformers (>=4.44.0,<5.0.0)
Project-URL: Documentation, https://benste.github.io/GraphRAGZen/
Project-URL: Repository, https://github.com/benste/GraphRAGZen/
